{
  "project_info": {
    "project_number": "523217010296",
    "project_id": "listadecontatos-4e1f9",
    "storage_bucket": "listadecontatos-4e1f9.appspot.com"
  },
  "client": [
    {
      "client_info": {
        "mobilesdk_app_id": "1:523217010296:android:33ce2cd394f3c96931778d",
        "android_client_info": {
          "package_name": "com.example.lista_contatos"
        }
      },
      "oauth_client": [],
      "api_key": [
        {
          "current_key": "AIzaSyC1QJRCzBoHdxTSBs4Zk_eEGBDGHGfsToo"
        }
      ],
      "services": {
        "appinvite_service": {
          "other_platform_oauth_client": []
        }
      }
    }
  ],
  "configuration_version": "1"
}